wayak_ai/__init__.py
wayak_ai/_base_client.py
wayak_ai/_client.py
wayak_ai/_compat.py
wayak_ai/_constants.py
wayak_ai/_exceptions.py
wayak_ai/_files.py
wayak_ai/_models.py
wayak_ai/_qs.py
wayak_ai/_resource.py
wayak_ai/_response.py
wayak_ai/_streaming.py
wayak_ai/_types.py
wayak_ai/_version.py
wayak_ai/py.typed
wayak_ai/_utils/__init__.py
wayak_ai/_utils/_logs.py
wayak_ai/_utils/_proxy.py
wayak_ai/_utils/_reflection.py
wayak_ai/_utils/_resources_proxy.py
wayak_ai/_utils/_streams.py
wayak_ai/_utils/_sync.py
wayak_ai/_utils/_transform.py
wayak_ai/_utils/_typing.py
wayak_ai/_utils/_utils.py
wayak_ai/lib/.keep
wayak_ai/resources/__init__.py
wayak_ai/resources/agents.py
wayak_ai/resources/brains.py
wayak_ai/resources/files.py
wayak_ai/resources/messages.py
wayak_ai/resources/threads.py
wayak_ai/resources/ontology/__init__.py
wayak_ai/resources/ontology/agent.py
wayak_ai/resources/ontology/dashboards.py
wayak_ai/resources/ontology/metrics.py
wayak_ai/resources/ontology/ontology.py
wayak_ai/resources/ontology/datasources/__init__.py
wayak_ai/resources/ontology/datasources/clickhouse.py
wayak_ai/resources/ontology/datasources/datasources.py
wayak_ai/resources/ontology/datasources/schema.py
wayak_ai/resources/organizations/__init__.py
wayak_ai/resources/organizations/members.py
wayak_ai/resources/organizations/organizations.py
wayak_ai/resources/projects/__init__.py
wayak_ai/resources/projects/files.py
wayak_ai/resources/projects/projects.py
wayak_ai/resources/users/__init__.py
wayak_ai/resources/users/context.py
wayak_ai/resources/users/profile.py
wayak_ai/resources/users/users.py
wayak_ai/types/__init__.py
wayak_ai/types/agent_extract_content_params.py
wayak_ai/types/agent_extract_content_response.py
wayak_ai/types/agent_get_completion_params.py
wayak_ai/types/agent_get_completion_response.py
wayak_ai/types/agent_list_supported_models_response.py
wayak_ai/types/agent_send_message_to_agent_params.py
wayak_ai/types/agent_send_message_to_wayak_params.py
wayak_ai-0.0.1a1.dist-info/METADATA
wayak_ai-0.0.1a1.dist-info/WHEEL
wayak_ai-0.0.1a1.dist-info/licenses/LICENSE
wayak_ai-0.0.1a1.dist-info/RECORD
